omtool/__init__.py
omtool/actions_after/__init__.py
omtool/actions_after/fit_action.py
omtool/actions_after/logger_action.py
omtool/actions_after/visualizer_action.py
omtool/actions_before/__init__.py
omtool/actions_before/barion_filter_action.py
omtool/actions_before/slice_action.py
omtool/analysis.py
omtool/core/__init__.py
omtool/core/configs/__init__.py
omtool/core/configs/analysis_config.py
omtool/core/configs/base_config.py
omtool/core/configs/creation_config.py
omtool/core/configs/integration_config.py
omtool/core/creation/__init__.py
omtool/core/creation/snapshot_builder.py
omtool/core/datamodel/__init__.py
omtool/core/datamodel/abstract_integrator.py
omtool/core/datamodel/abstract_model.py
omtool/core/datamodel/abstract_task.py
omtool/core/datamodel/handler_task.py
omtool/core/datamodel/snapshot.py
omtool/core/datamodel/task_profiler.py
omtool/core/integrators/__init__.py
omtool/core/integrators/config.py
omtool/core/models/__init__.py
omtool/core/models/config.py
omtool/core/tasks/__init__.py
omtool/core/tasks/config.py
omtool/core/utils/__init__.py
omtool/core/utils/config_utils.py
omtool/core/utils/galactic_utils.py
omtool/core/utils/logger_utils.py
omtool/core/utils/math.py
omtool/core/utils/particle_centers.py
omtool/core/utils/pyfalcon_analizer.py
omtool/creator.py
omtool/integration.py
omtool/io_service/__init__.py
omtool/io_service/config.py
omtool/io_service/main.py
omtool/io_service/readers.py
omtool/visualizer/__init__.py
omtool/visualizer/config.py
omtool/visualizer/draw_parameters.py
omtool/visualizer/main.py
omtool/visualizer/visualizer.py
omtool-0.2.0.dist-info/LICENSE
omtool-0.2.0.dist-info/WHEEL
omtool-0.2.0.dist-info/METADATA
omtool-0.2.0.dist-info/RECORD
