Metadata-Version: 2.1
Name: omtool
Version: 0.2.0
Summary: Package and program that models N-Body problem in galactic evolution application.
Home-page: https://github.com/Kraysent/OMTool
License: Apache-2.0
Author: Artyom Zaporozhets
Author-email: kraysent@gmail.com
Requires-Python: >=3.10,<4.0
Classifier: License :: OSI Approved :: Apache Software License
Classifier: Programming Language :: Python :: 3
Classifier: Programming Language :: Python :: 3.10
Provides-Extra: tasks
Requires-Dist: PyYAML (>=6.0,<7.0)
Requires-Dist: amuse-framework (>=2022.6.0,<2023.0.0)
Requires-Dist: astropy (>=5.1,<6.0)
Requires-Dist: marshmallow (>=3.17.0,<4.0.0)
Requires-Dist: marshmallow-jsonschema (>=0.13.0,<0.14.0)
Requires-Dist: matplotlib (>=3.5.2,<4.0.0)
Requires-Dist: numpy (>=1.23.1,<2.0.0)
Requires-Dist: pandas (>=1.4.3,<2.0.0)
Requires-Dist: py-expression-eval (>=0.3.14,<0.4.0); extra == "tasks"
Requires-Dist: pyzerolog (>=0.3.0,<0.4.0)
Project-URL: Documentation, https://omtool.readthedocs.io/en/latest/
Project-URL: Repository, https://github.com/Kraysent/OMTool
